{"session_file": "+37128787428", "phone": "+37128787428", "register_time": 1638974590, "app_id": 6, "app_hash": "eb06d4abfb49dc3eeb1aeb98ae0f581e", "sdk": "SDK 26", "app_version": "7.6.0 (22642)", "device": "samsungSM-G960F", "lang_pack": "android", "success_registred": true, "proxy": null, "register_process": false, "first_name": "Тарас", "last_name": "Козаченко", "last_check_time": 1640693188, "deleted": false, "username": "anschutz10", "avatar": "./avatars/3.jpeg", "password": true, "password_str": "201088"}